[{"senderKeyId":2112223248,"senderChainKey":{"iteration":215,"seed":"20lS+tsEm1/w9CnmCdKV/UspGfttpqb8AU1AL9tzx3A="},"senderSigningKey":{"public":"Bd/yhFhiFcbVP55ZTk0oQ9D2xRlVRe7Aj9RrRKVI4C8U","private":"iDEeAhee7OcQcv7800gDdVI9FHoQQZDUWPQo0KNjnXE="},"senderMessageKeys":[{},{},{},{},{},{},{},{},{},{},{},{},{},{},{},{},{},{},{},{},{},{},{},{},{},{},{},{},{},{},{},{},{},{},{},{},{},{},{},{},{},{},{},{},{},{},{},{},{},{},{},{},{},{},{},{},{},{},{},{},{},{},{},{},{},{},{},{},{},{},{},{},{},{},{},{},{},{},{},{},{},{},{},{},{},{},{},{},{},{},{},{},{},{},{},{},{},{},{},{},{},{},{},{},{},{},{}]}]